evoc/__init__.py
evoc/boruvka.py
evoc/cluster_trees.py
evoc/clustering.py
evoc/common_nndescent.py
evoc/disjoint_set.py
evoc/float_nndescent.py
evoc/graph_construction.py
evoc/int8_nndescent.py
evoc/knn_graph.py
evoc/label_propagation.py
evoc/node_embedding.py
evoc/numba_kdtree.py
evoc/uint8_nndescent.py
evoc-0.1.3.dist-info/LICENSE
evoc-0.1.3.dist-info/METADATA
evoc-0.1.3.dist-info/WHEEL
evoc-0.1.3.dist-info/top_level.txt
evoc-0.1.3.dist-info/RECORD
