Metadata-Version: 2.1
Name: evoc
Version: 0.1.3
Summary: Embedding Vector Oriented Clustering
Home-page: https://github.com/TutteInstitute/evoc
Author: Leland McInnes
Author-email: leland.mcinnes@gmail.com
Maintainer: Leland McInnes
Maintainer-email: leland.mcinnes@gmail.com
License: BSD License
Keywords: embedding vector,vector database,topic modelling,cluster,clustering
Classifier: License :: OSI Approved :: BSD License
Classifier: Programming Language :: Python :: 3.10
Classifier: Programming Language :: Python :: 3.11
Classifier: Programming Language :: Python :: 3.12
Classifier: Development Status :: 4 - Beta
Classifier: Operating System :: OS Independent
Requires-Python: >=3.10
License-File: LICENSE
Requires-Dist: numpy>=1.21
Requires-Dist: scikit-learn>=1.1
Requires-Dist: numba>=0.59
Requires-Dist: tqdm
